power_query/__init__.py
power_query/admin.py
power_query/apps.py
power_query/celery_tasks.py
power_query/defaults.py
power_query/exceptions.py
power_query/fixtures.py
power_query/forms.py
power_query/json.py
power_query/mixin.py
power_query/models.py
power_query/notify.py
power_query/signals.py
power_query/urls.py
power_query/utils.py
power_query/validators.py
power_query/views.py
power_query/widget.py
power_query/__pycache__/__init__.cpython-311.pyc
power_query/__pycache__/__init__.cpython-39.pyc
power_query/__pycache__/admin.cpython-311.pyc
power_query/__pycache__/admin.cpython-39.pyc
power_query/__pycache__/apps.cpython-311.pyc
power_query/__pycache__/apps.cpython-39.pyc
power_query/__pycache__/celery_tasks.cpython-311.pyc
power_query/__pycache__/celery_tasks.cpython-39.pyc
power_query/__pycache__/defaults.cpython-311.pyc
power_query/__pycache__/defaults.cpython-39.pyc
power_query/__pycache__/exceptions.cpython-311.pyc
power_query/__pycache__/exceptions.cpython-39.pyc
power_query/__pycache__/fixtures.cpython-311.pyc
power_query/__pycache__/fixtures.cpython-39.pyc
power_query/__pycache__/forms.cpython-311.pyc
power_query/__pycache__/forms.cpython-39.pyc
power_query/__pycache__/json.cpython-311.pyc
power_query/__pycache__/json.cpython-39.pyc
power_query/__pycache__/mixin.cpython-39.pyc
power_query/__pycache__/models.cpython-311.pyc
power_query/__pycache__/models.cpython-39.pyc
power_query/__pycache__/urls.cpython-311.pyc
power_query/__pycache__/urls.cpython-39.pyc
power_query/__pycache__/utils.cpython-311.pyc
power_query/__pycache__/utils.cpython-39.pyc
power_query/__pycache__/validators.cpython-311.pyc
power_query/__pycache__/validators.cpython-39.pyc
power_query/__pycache__/views.cpython-311.pyc
power_query/__pycache__/views.cpython-39.pyc
power_query/__pycache__/widget.cpython-311.pyc
power_query/__pycache__/widget.cpython-39.pyc
power_query/management/__init__.py
power_query/management/__pycache__/__init__.cpython-311.pyc
unicef_power_query-0.4.dist-info/LICENSE
unicef_power_query-0.4.dist-info/METADATA
unicef_power_query-0.4.dist-info/WHEEL
unicef_power_query-0.4.dist-info/top_level.txt
unicef_power_query-0.4.dist-info/RECORD
