Metadata-Version: 2.1
Name: unicef-power-query
Version: 0.4
Summary: Provides Basic UNICEF User model and integration with Azure
Home-page: https://github.com/unicef/unicef-power-query
Author: UNICEF
License: Apache 2 License
Platform: any
Classifier: Environment :: Web Environment
Classifier: Programming Language :: Python :: 3.9
Classifier: Framework :: Django
Classifier: Framework :: Django :: 3.2
Classifier: Framework :: Django :: 4.2
Classifier: Intended Audience :: Developers
License-File: LICENSE
Requires-Dist: celery
Requires-Dist: django
Requires-Dist: django-admin-extra-buttons
Requires-Dist: django-adminfilters
Requires-Dist: django-adminactions
Requires-Dist: django-concurrency
Requires-Dist: django-import-export
Requires-Dist: django-smart-admin
Requires-Dist: kombu
Requires-Dist: natural-keys
Requires-Dist: tablib
Requires-Dist: PyPDF2
Requires-Dist: pdfkit
Requires-Dist: redis
Requires-Dist: sentry-sdk
Provides-Extra: test
Requires-Dist: black ; extra == 'test'
Requires-Dist: django-webtest ; extra == 'test'
Requires-Dist: factory-boy ; extra == 'test'
Requires-Dist: flake8 ; extra == 'test'
Requires-Dist: freezegun ; extra == 'test'
Requires-Dist: isort ; extra == 'test'
Requires-Dist: parameterized ; extra == 'test'
Requires-Dist: pytest ; extra == 'test'
Requires-Dist: pytest-coverage ; extra == 'test'
Requires-Dist: pytest-django ; extra == 'test'
Requires-Dist: pytest-echo ; extra == 'test'
Requires-Dist: psycopg2 ; extra == 'test'
